feat_engine/__init__.py
feat_engine/cluster_data.py
feat_engine/encode_category.py
feat_engine/group_features.py
feat_engine/handle_missing_values.py
feat_engine/handle_outliers.py
feat_engine/interact_features.py
feat_engine/normalize_scaling.py
feat_engine/operate_dataframe.py
feat_engine/reduce_dimension.py
feat_engine/select_features.py
feat_engine/solve_classification.py
feat_engine/solve_regression.py
feat_engine/target_based_features.py
feat_engine/temporal_features.py
feat_engine/transform_features.py
feat_engine/visualize_data.py
feat_engine-1.0.2.dist-info/LICENSE
feat_engine-1.0.2.dist-info/METADATA
feat_engine-1.0.2.dist-info/WHEEL
feat_engine-1.0.2.dist-info/RECORD
