Metadata-Version: 2.1
Name: feat-engine
Version: 1.0.2
Summary: 
Author: Ryota Kobayashi
Author-email: s.woods.m.29@gmail.com
Requires-Python: >=3.9,<3.12
Classifier: Programming Language :: Python :: 3
Classifier: Programming Language :: Python :: 3.9
Classifier: Programming Language :: Python :: 3.10
Classifier: Programming Language :: Python :: 3.11
Requires-Dist: catboost (>=1.2.7,<2.0.0)
Requires-Dist: category-encoders (>=2.6.3,<3.0.0)
Requires-Dist: imblearn (>=0.0,<0.1)
Requires-Dist: lightgbm (>=4.5.0,<5.0.0)
Requires-Dist: matplotlib (>=3.9.2,<4.0.0)
Requires-Dist: nbformat (>=5.10.4,<6.0.0)
Requires-Dist: optuna (>=4.0.0,<5.0.0)
Requires-Dist: pandas (>=2.2.2,<3.0.0)
Requires-Dist: plotly (>=5.24.0,<6.0.0)
Requires-Dist: pytest (>=8.3.2,<9.0.0)
Requires-Dist: pytk (>=0.0.2.1,<0.0.3.0)
Requires-Dist: scikit-learn (>=1.5.1,<2.0.0)
Requires-Dist: seaborn (>=0.13.2,<0.14.0)
Requires-Dist: setuptools (>=74.1.2,<75.0.0)
Requires-Dist: sphinx (<8)
Requires-Dist: sphinx-autobuild (>=2024.9.3,<2025.0.0)
Requires-Dist: sphinx-rtd-theme (>=2.0.0,<3.0.0)
Requires-Dist: tensorflow (>=2.17,<2.18)
Requires-Dist: tensorflow-io-gcs-filesystem (==0.31.0)
Requires-Dist: tk (>=0.1.0,<0.2.0)
Requires-Dist: twine (>=5.1.1,<6.0.0)
Requires-Dist: umap (>=0.1.1,<0.2.0)
Requires-Dist: umap-learn (>=0.5.6,<0.6.0)
Requires-Dist: wheel (>=0.44.0,<0.45.0)
Requires-Dist: xgboost (>=2.1.1,<3.0.0)
